my_streamlit/__init__.py
streamlit_study-0.1.0.dist-info/METADATA
streamlit_study-0.1.0.dist-info/WHEEL
streamlit_study-0.1.0.dist-info/top_level.txt
streamlit_study-0.1.0.dist-info/RECORD
