Metadata-Version: 2.1
Name: streamlit-study
Version: 0.1.0
Summary: Stre;amlit package
Author-email: hun0219 <gsw98000@gmail.com>
License: MIT
Project-URL: github, https://github.com/hun0219/streamlit_hun0219
Requires-Python: >=3.9
